data/strokeCount.json
strokes/__init__.py
strokes/strokes.py
strokes-0.0.1.dist-info/METADATA
strokes-0.0.1.dist-info/WHEEL
strokes-0.0.1.dist-info/top_level.txt
strokes-0.0.1.dist-info/RECORD
