Metadata-Version: 2.1
Name: strokes
Version: 0.0.1
Summary: Hanzi stroke counts
Home-page: https://github.com/liao961120/strokes
Author: Yongfu Liao
Author-email: liao961120@gmail.com
License: UNKNOWN
Platform: UNKNOWN
Classifier: Programming Language :: Python :: 3
Classifier: License :: OSI Approved :: MIT License
Classifier: Operating System :: OS Independent
